lumaapi/__init__.py
scripts/run_lumaapi.py
lumaapi-0.0.5.dist-info/METADATA
lumaapi-0.0.5.dist-info/WHEEL
lumaapi-0.0.5.dist-info/entry_points.txt
lumaapi-0.0.5.dist-info/top_level.txt
lumaapi-0.0.5.dist-info/RECORD
