Metadata-Version: 2.1
Name: lumaapi
Version: 0.0.5
Summary: Luma AI captures API wrapper library and CLI (deprecated, please install lumaai for dream machine API)
Author-email: Luma AI <hello@lumalabs.ai>
License: MIT
Project-URL: Homepage, https://lumalabs.ai/luma-api
Classifier: License :: OSI Approved :: MIT License
Classifier: Programming Language :: Python :: 3
Requires-Python: >=3.7
Requires-Dist: requests
Requires-Dist: fire
Requires-Dist: enum-tools
Requires-Dist: platformdirs
